{
  "generatedAt": "2026-05-03T02:54:26.807Z",
  "status": "warning",
  "thresholds": {
    "minPlayers": 24,
    "minTeams": 12,
    "minLegacy": 8,
    "maxStaleHours": 168,
    "requireLiveData": false
  },
  "metrics": {
    "players": 80,
    "teams": 20,
    "legacy": 16,
    "teamStrength": 0,
    "entityTeams": 0,
    "playerEnrichment": 80
  },
  "datasets": {
    "fixtures": {
      "count": 0,
      "generatedAt": "2026-05-03T02:54:17.878Z",
      "staleHours": 0,
      "freshness": "ok",
      "sourceStatus": {
        "footballData": {
          "status": "ok",
          "fetchedAt": "2026-05-03T02:54:17.878Z"
        }
      }
    },
    "standings": {
      "count": 0,
      "generatedAt": "2026-05-03T02:54:17.878Z",
      "staleHours": 0,
      "freshness": "ok",
      "sourceStatus": {
        "footballData": {
          "status": "ok",
          "fetchedAt": "2026-05-03T02:54:17.878Z"
        }
      }
    },
    "fantasy": {
      "count": 80,
      "generatedAt": "2026-03-07T07:13:03.301Z",
      "staleHours": 1363.69,
      "freshness": "warn",
      "sourceStatus": {
        "footballData": {
          "status": "fallback",
          "message": "Derived from local players + fixture competition mapping.",
          "fetchedAt": "2026-03-07T07:13:03.301Z"
        },
        "playersSeed": {
          "status": "ok",
          "fetchedAt": "2026-03-07T07:13:03.301Z"
        }
      }
    },
    "archive": {
      "count": 85,
      "generatedAt": "2026-05-03T02:54:24.631Z",
      "staleHours": 0,
      "freshness": "ok",
      "sourceStatus": {
        "statsbomb": {
          "status": "ok",
          "fetchedAt": "2026-05-03T02:54:24.136Z",
          "competitionCount": 75
        },
        "openfootball": {
          "status": "ok",
          "fetchedAt": "2026-05-03T02:54:24.622Z",
          "sourceCount": 10
        }
      }
    }
  },
  "criticalIssues": [],
  "warnings": [
    "fixtures appears empty (count=0)",
    "standings appears empty (count=0)",
    "fantasy data is stale (1364h old)",
    "team-strength dataset is empty",
    "entity-metadata dataset is empty"
  ]
}
